gandalf/__init__.py
gandalf/console.py
gandalf/main.py
gandalf/metadata.py
gandalf-0.1.4.dist-info/LICENSE.md
gandalf-0.1.4.dist-info/METADATA
gandalf-0.1.4.dist-info/WHEEL
gandalf-0.1.4.dist-info/entry_points.txt
gandalf-0.1.4.dist-info/top_level.txt
gandalf-0.1.4.dist-info/RECORD
